{"assets":{"DB8451458D98EFA7506DBEBC2B1323F0":{"type":"texture","index":1,"assetRequest":{"type":"slide","state":"contents","slide":"none"},"url":{"native":"assets/AE0B56AF-C0EC-47C7-889E-94BAF6E8C128.pdf"},"width":1024,"height":768},"A337C2461B759678EF6C381F724E5825":{"type":"texture","index":0,"assetRequest":{"type":"slide","state":"contents","slide":"none"},"url":{"native":"assets/AE0B56AF-C0EC-47C7-889E-94BAF6E8C128.pdf"},"width":1024,"height":768}},"events":[{"effects":[{"beginTime":0,"baseLayer":{"animations":[],"initialState":{"affineTransform":[1,0,0,1,0,0],"masksToBounds":false,"rotation":0,"scale":1,"position":{"pointX":512,"pointY":384},"width":1024,"sublayerTransform":[1,0,0,0,0,1,0,0,0,0,1,0,0,0,0,1],"contentsRect":{"y":0,"x":0,"width":1,"height":1},"opacity":1,"edgeAntialiasingMask":251658240,"height":768,"hidden":false,"anchorPoint":{"pointX":0.5,"pointY":0.5}},"objectID":"0","layers":[{"animations":[],"initialState":{"affineTransform":[1,0,0,1,0,0],"masksToBounds":false,"rotation":0,"scale":1,"position":{"pointX":512,"pointY":384},"width":1024,"sublayerTransform":[1,0,0,0,0,1,0,0,0,0,1,-0.0004922987690640373,0,0,0,1],"contentsRect":{"y":0,"x":0,"width":1,"height":1},"opacity":1,"edgeAntialiasingMask":251658240,"height":768,"hidden":false,"anchorPoint":{"pointX":0.5,"pointY":0.5}},"layers":[{"animations":[],"layers":[],"texturedRectangle":{"isBackgroundTexture":false,"singleTextureOpacity":1,"textureType":0,"textBaseline":0,"textXHeight":0,"isVerticalText":false},"initialState":{"affineTransform":[1,0,0,1,0,0],"masksToBounds":false,"rotation":0,"scale":1,"position":{"pointX":512,"pointY":384},"width":1024,"sublayerTransform":[1,0,0,0,0,1,0,0,0,0,1,0,0,0,0,1],"contentsRect":{"y":0,"x":0,"width":1,"height":1},"opacity":1,"edgeAntialiasingMask":0,"height":768,"hidden":false,"anchorPoint":{"pointX":0.5,"pointY":0.5}},"texture":"DB8451458D98EFA7506DBEBC2B1323F0"},{"animations":[{"timeOffset":0,"from":{"scalar":false},"beginTime":0,"repeatCount":0,"fillMode":"both","property":"hidden","autoreverses":false,"duration":0.01,"to":{"scalar":true}}],"layers":[],"texturedRectangle":{"isBackgroundTexture":false,"singleTextureOpacity":1,"textureType":0,"textBaseline":0,"textXHeight":0,"isVerticalText":false},"initialState":{"affineTransform":[1,0,0,1,0,0],"masksToBounds":false,"rotation":0,"scale":1,"position":{"pointX":512,"pointY":384},"width":1024,"sublayerTransform":[1,0,0,0,0,1,0,0,0,0,1,0,0,0,0,1],"contentsRect":{"y":0,"x":0,"width":1,"height":1},"opacity":1,"edgeAntialiasingMask":0,"height":768,"hidden":false,"anchorPoint":{"pointX":0.5,"pointY":0.5}},"texture":"A337C2461B759678EF6C381F724E5825"}]}]},"effects":[],"duration":0.01,"type":"transition","name":"none","objectID":"0"}],"automaticPlay":false,"hyperlinks":[{"url":"mailto:brian.cohn@usc.edu","targetRectangle":{"y":40.80046510696411,"x":598.3860287666321,"width":341.8559999999999,"height":43}},{"url":"http://valerolab.org","targetRectangle":{"y":81.13317155838013,"x":656.7960295677185,"width":225.0360000000001,"height":43}}],"accessibility":[{"text":"System for cataloging the properties of cadaveric and robotic limbs alike, with cadaver studies scheduled for Fall 2017.","targetRectangle":{"y":159.1652679443359,"x":103.1499999165535,"width":791.1263999999999,"height":56}},{"text":"A 35GB dataset with 98 million tension-to-force observations on a robotic limb, with 1200 different endpoint postures in the workspace.","targetRectangle":{"y":215.1652679443359,"x":103.1499999165535,"width":846.79008,"height":84.9799998998642}},{"text":"Evidence that feasibility spaces approximate tendon-driven force control.","targetRectangle":{"y":300.1452678442001,"x":103.1499999165535,"width":737.5824000000002,"height":56.9799998998642}},{"text":"Data to simulate afferent signals of muscle spindles and Golgi organs in future studies.","targetRectangle":{"y":357.1252677440643,"x":103.1499999165535,"width":869.4220800000004,"height":56.9799998998642}},{"text":"brian.cohn@usc.edu","targetRectangle":{"y":40.80046510696411,"x":598.3860287666321,"width":341.8559999999999,"height":43}},{"text":"pasted-image.png","targetRectangle":{"y":421.6032409667969,"x":-0.6505088210105896,"width":517.9024047851562,"height":429.9189758300781}},{"text":"pasted-image.png","targetRectangle":{"y":421.622802734375,"x":446.9819947356531,"width":710,"height":429.8827108740807}},{"text":"Overview","targetRectangle":{"y":40.44097924232483,"x":158.8134887695312,"width":346.4000000000001,"height":96}},{"text":"valerolab.org","targetRectangle":{"y":81.13317155838013,"x":656.7960295677185,"width":225.0360000000001,"height":43}}],"baseLayer":{"animations":[],"initialState":{"affineTransform":[1,0,0,1,0,0],"masksToBounds":false,"rotation":0,"scale":1,"position":{"pointX":512,"pointY":384},"width":1024,"sublayerTransform":[1,0,0,0,0,1,0,0,0,0,1,0,0,0,0,1],"contentsRect":{"y":0,"x":0,"width":1,"height":1},"opacity":1,"edgeAntialiasingMask":251658240,"height":768,"hidden":false,"anchorPoint":{"pointX":0.5,"pointY":0.5}},"objectID":"0","layers":[{"animations":[],"initialState":{"affineTransform":[1,0,0,1,0,0],"masksToBounds":false,"rotation":0,"scale":1,"position":{"pointX":512,"pointY":384},"width":1024,"sublayerTransform":[1,0,0,0,0,1,0,0,0,0,1,-0.0004922987690640373,0,0,0,1],"contentsRect":{"y":0,"x":0,"width":1,"height":1},"opacity":1,"edgeAntialiasingMask":251658240,"height":768,"hidden":false,"anchorPoint":{"pointX":0.5,"pointY":0.5}},"layers":[{"animations":[],"layers":[],"texturedRectangle":{"isBackgroundTexture":false,"singleTextureOpacity":1,"textureType":0,"textBaseline":0,"textXHeight":0,"isVerticalText":false},"initialState":{"affineTransform":[1,0,0,1,0,0],"masksToBounds":false,"rotation":0,"scale":1,"position":{"pointX":512,"pointY":384},"width":1024,"sublayerTransform":[1,0,0,0,0,1,0,0,0,0,1,0,0,0,0,1],"contentsRect":{"y":0,"x":0,"width":1,"height":1},"opacity":1,"edgeAntialiasingMask":0,"height":768,"hidden":false,"anchorPoint":{"pointX":0.5,"pointY":0.5}},"texture":"A337C2461B759678EF6C381F724E5825"}]}]}}]}